{
  "name": "📊 Zerodha Monitor — Every 5 Min",
  "nodes": [

    {
      "id": "mon-trigger",
      "name": "⏱️ Every 5 Min (9:50–3:20)",
      "type": "n8n-nodes-base.scheduleTrigger",
      "typeVersion": 1.2,
      "position": [100, 300],
      "parameters": {
        "rule": {
          "interval": [{ "field": "cronExpression", "expression": "*/5 9-15 * * 1-5" }]
        }
      }
    },

    {
      "id": "mon-load-state",
      "name": "📂 Load Active Trades State",
      "type": "n8n-nodes-base.code",
      "typeVersion": 2,
      "position": [340, 300],
      "parameters": {
        "jsCode": "// ═══════════════════════════════════════════════════\n// Reads active_trades.json written by MAIN workflow\n// This is how Monitor knows what was bought today\n// ═══════════════════════════════════════════════════\nconst fs = require('fs');\nconst path = require('path');\nconst STATE_FILE = path.join(process.env.HOME||'/root', 'autotrader', 'active_trades.json');\nconst today = new Date().toISOString().split('T')[0];\n\nlet state = null;\ntry {\n  state = JSON.parse(fs.readFileSync(STATE_FILE, 'utf8'));\n} catch(e) {\n  return [{ json: { skip: true, reason: 'No state file yet — MAIN workflow not run today', today } }];\n}\n\n// Skip if state is from a different day or session already closed\nif (state.date !== today) {\n  return [{ json: { skip: true, reason: 'State file is from ' + state.date + ' not today', today } }];\n}\nif (state.sessionClosed) {\n  return [{ json: { skip: true, reason: 'Session already closed for today', today } }];\n}\n\nconst openTrades = (state.trades||[]).filter(t => t.status === 'OPEN');\nif (openTrades.length === 0) {\n  return [{ json: { skip: true, reason: 'No open trades to monitor', today } }];\n}\n\nreturn [{ json: { ...state, openTrades, stateFile: STATE_FILE, skip: false } }];"
      }
    },

    {
      "id": "mon-skip-check",
      "name": "🔍 Skip if No Open Trades?",
      "type": "n8n-nodes-base.if",
      "typeVersion": 2,
      "position": [580, 300],
      "parameters": {
        "conditions": {
          "conditions": [{ "leftValue": "={{ $json.skip }}", "rightValue": false, "operator": { "type": "boolean", "operation": "true" } }],
          "combinator": "and"
        }
      }
    },

    {
      "id": "mon-fetch-prices",
      "name": "📈 Fetch Live Prices — Zerodha",
      "type": "n8n-nodes-base.httpRequest",
      "typeVersion": 4.2,
      "position": [820, 180],
      "parameters": {
        "method": "GET",
        "url": "=https://api.kite.trade/quote?i={{ $json.openTrades.map(t=>'NSE:'+t.symbol).join('&i=') }}",
        "sendHeaders": true,
        "headerParameters": {
          "parameters": [
            { "name": "X-Kite-Version", "value": "3" },
            { "name": "Authorization",  "value": "=token {{ $json.ZERODHA_API_KEY }}:{{ $json.ZERODHA_ACCESS_TOKEN }}" }
          ]
        },
        "options": { "response": { "response": { "neverError": true } } }
      },
      "continueOnFail": true
    },

    {
      "id": "mon-evaluate",
      "name": "💰 Evaluate P&L + Exit Decisions",
      "type": "n8n-nodes-base.code",
      "typeVersion": 2,
      "position": [1060, 300],
      "parameters": {
        "jsCode": "// ═══════════════════════════════════════════════════\n// Core monitor logic:\n// 1. Compare live price vs target / stop-loss\n// 2. Flag trades to exit\n// 3. Check IST time for EOD squareoff (3:10 PM)\n// 4. Update state file\n// ═══════════════════════════════════════════════════\nconst fs = require('fs');\nconst data = items[0].json;\nconst liveData = data.data || {};\nconst openTrades = data.openTrades || [];\nconst STATE_FILE = data.stateFile;\n\n// Current IST time\nconst now = new Date();\nconst istStr = now.toLocaleString('en-IN', { timeZone: 'Asia/Kolkata', hour: 'numeric', minute: 'numeric', hour12: false });\nconst [istH, istM] = istStr.split(':').map(Number);\nconst isEOD = istH === 15 && istM >= 10;  // 3:10 PM or later\nconst timeStr = now.toLocaleString('en-IN', { timeZone: 'Asia/Kolkata' });\n\nconst toSell = [];    // trades that hit target or SL\nconst stillOpen = []; // trades still active\nlet totalPnL = 0;\n\nfor (const trade of openTrades) {\n  const key = 'NSE:' + trade.symbol;\n  const ltp = liveData[key]?.last_price || trade.entryPrice;\n  const pnl = (ltp - trade.entryPrice) * trade.qty;\n  const pnlPct = ((ltp - trade.entryPrice) / trade.entryPrice) * 100;\n  totalPnL += pnl;\n\n  const hitTarget = ltp >= trade.target;\n  const hitSL     = ltp <= trade.stopLoss;\n  const exitEOD   = isEOD;\n\n  if (hitTarget || hitSL || exitEOD) {\n    toSell.push({\n      ...trade, ltp, pnl: +pnl.toFixed(2), pnlPct: +pnlPct.toFixed(2),\n      exitReason: hitTarget ? 'TARGET_HIT' : hitSL ? 'STOPLOSS_HIT' : 'EOD_SQUAREOFF',\n      exitTime: timeStr, status: 'CLOSING'\n    });\n  } else {\n    stillOpen.push({ ...trade, ltp, pnl: +pnl.toFixed(2), pnlPct: +pnlPct.toFixed(2) });\n  }\n}\n\n// All targets hit = session done early\nconst allTargetsHit = openTrades.length > 0 &&\n  toSell.every(t => t.exitReason === 'TARGET_HIT') &&\n  stillOpen.length === 0;\n\n// Update state file\nif (STATE_FILE) {\n  try {\n    const state = JSON.parse(fs.readFileSync(STATE_FILE, 'utf8'));\n    state.trades = [\n      ...toSell.map(t => ({ ...t, status: 'CLOSED' })),\n      ...stillOpen\n    ];\n    state.lastMonitorAt = now.toISOString();\n    state.sessionClosed = isEOD || stillOpen.length === 0;\n    state.totalPnL = +totalPnL.toFixed(2);\n    fs.writeFileSync(STATE_FILE, JSON.stringify(state, null, 2));\n  } catch (e) { console.log('State update error:', e.message); }\n}\n\nreturn [{\n  json: {\n    ...data,\n    toSell, stillOpen, totalPnL: +totalPnL.toFixed(2),\n    hasExits: toSell.length > 0,\n    allTargetsHit, isEOD, timeStr\n  }\n}];"
      }
    },

    {
      "id": "mon-has-exits",
      "name": "🔍 Any Exits Needed?",
      "type": "n8n-nodes-base.if",
      "typeVersion": 2,
      "position": [1300, 300],
      "parameters": {
        "conditions": {
          "conditions": [{ "leftValue": "={{ $json.hasExits }}", "rightValue": true, "operator": { "type": "boolean", "operation": "true" } }],
          "combinator": "and"
        }
      }
    },

    {
      "id": "mon-split-exits",
      "name": "🔀 Split — One Per Exit Trade",
      "type": "n8n-nodes-base.code",
      "typeVersion": 2,
      "position": [1540, 180],
      "parameters": {
        "jsCode": "const data = items[0].json;\nreturn (data.toSell||[]).map(t => ({ json: { ...data, currentExit: t } }));"
      }
    },

    {
      "id": "mon-sell-order",
      "name": "📤 Kite — Place SELL",
      "type": "n8n-nodes-base.httpRequest",
      "typeVersion": 4.2,
      "position": [1780, 100],
      "parameters": {
        "method": "POST",
        "url": "https://api.kite.trade/orders/regular",
        "sendHeaders": true,
        "headerParameters": {
          "parameters": [
            { "name": "X-Kite-Version", "value": "3" },
            { "name": "Authorization",  "value": "=token {{ $json.ZERODHA_API_KEY }}:{{ $json.ZERODHA_ACCESS_TOKEN }}" }
          ]
        },
        "sendBody": true,
        "contentType": "form-urlencoded",
        "bodyParameters": {
          "parameters": [
            { "name": "tradingsymbol",    "value": "={{ $json.currentExit.symbol }}" },
            { "name": "exchange",         "value": "NSE" },
            { "name": "transaction_type", "value": "SELL" },
            { "name": "order_type",       "value": "MARKET" },
            { "name": "product",          "value": "MIS" },
            { "name": "quantity",         "value": "={{ $json.currentExit.qty }}" },
            { "name": "validity",         "value": "DAY" },
            { "name": "tag",              "value": "AutoTrader-Exit" }
          ]
        },
        "options": { "response": { "response": { "neverError": true } } }
      },
      "continueOnFail": true
    },

    {
      "id": "mon-build-exit-msg",
      "name": "📝 Build Exit Alert",
      "type": "n8n-nodes-base.code",
      "typeVersion": 2,
      "position": [2020, 180],
      "parameters": {
        "jsCode": "const data = items[0].json;\nconst exits = data.toSell||[];\nconst still = data.stillOpen||[];\nconst emoji = r => r==='TARGET_HIT'?'🎯':r==='STOPLOSS_HIT'?'🛑':'⏰';\nconst exitLines = exits.map(t=>`${emoji(t.exitReason)} *${t.symbol}* — ${t.exitReason.replace('_',' ')}\\n   Entry:₹${t.entryPrice} Exit:₹${t.ltp} P&L:${t.pnl>=0?'+':''}₹${t.pnl}(${t.pnlPct>=0?'+':''}${t.pnlPct}%)`).join('\\n');\nconst openLines = still.length?'\\n⏳ Still open: '+still.map(t=>`${t.symbol}(₹${t.ltp} ${t.pnlPct>=0?'+':''}${t.pnlPct}%)`).join(', '):'\\nAll positions closed.';\nconst totalStr = `Total P&L: ${data.totalPnL>=0?'+':''}₹${data.totalPnL}`;\nconst sessionMsg = data.allTargetsHit?'\\n🏆 ALL TARGETS HIT — Session complete! Great day!':''\nconst msg=`📊 *AUTO-TRADER EXIT*\\n${data.timeStr}\\n━━━━━━━━━━━━━━\\n${exitLines}\\n${openLines}\\n━━━━━━━━━━━━━━\\n${totalStr}${sessionMsg}`;\nreturn[{json:{...data,exitMessage:msg}}];"
      }
    },

    {
      "id": "mon-whatsapp-exit",
      "name": "📱 WhatsApp — Exit Alert",
      "type": "n8n-nodes-base.httpRequest",
      "typeVersion": 4.2,
      "position": [2260, 180],
      "parameters": {
        "method": "POST",
        "url": "=https://api.twilio.com/2010-04-01/Accounts/{{ $json.TWILIO_ACCOUNT_SID }}/Messages.json",
        "sendHeaders": true,
        "headerParameters": {
          "parameters": [{ "name": "Authorization", "value": "=Basic {{ Buffer.from($json.TWILIO_ACCOUNT_SID + ':' + $json.TWILIO_AUTH_TOKEN).toString('base64') }}" }]
        },
        "sendBody": true,
        "contentType": "form-urlencoded",
        "bodyParameters": {
          "parameters": [
            { "name": "From", "value": "={{ $json.TWILIO_WHATSAPP_FROM }}" },
            { "name": "To",   "value": "={{ $json.ALERT_PHONE }}" },
            { "name": "Body", "value": "={{ $json.exitMessage }}" }
          ]
        },
        "options": { "response": { "response": { "neverError": true } } }
      },
      "continueOnFail": true
    }

  ],

  "connections": {
    "⏱️ Every 5 Min (9:50–3:20)":         { "main": [[{ "node": "📂 Load Active Trades State",      "type": "main", "index": 0 }]] },
    "📂 Load Active Trades State":         { "main": [[{ "node": "🔍 Skip if No Open Trades?",        "type": "main", "index": 0 }]] },
    "🔍 Skip if No Open Trades?":          { "main": [[{ "node": "📈 Fetch Live Prices — Zerodha",   "type": "main", "index": 0 }], []] },
    "📈 Fetch Live Prices — Zerodha":      { "main": [[{ "node": "💰 Evaluate P&L + Exit Decisions", "type": "main", "index": 0 }]] },
    "💰 Evaluate P&L + Exit Decisions":   { "main": [[{ "node": "🔍 Any Exits Needed?",              "type": "main", "index": 0 }]] },
    "🔍 Any Exits Needed?":               { "main": [[{ "node": "🔀 Split — One Per Exit Trade",     "type": "main", "index": 0 }], []] },
    "🔀 Split — One Per Exit Trade":      { "main": [[{ "node": "📤 Kite — Place SELL",              "type": "main", "index": 0 }]] },
    "📤 Kite — Place SELL":               { "main": [[{ "node": "📝 Build Exit Alert",               "type": "main", "index": 0 }]] },
    "📝 Build Exit Alert":                { "main": [[{ "node": "📱 WhatsApp — Exit Alert",           "type": "main", "index": 0 }]] }
  },

  "settings": { "executionOrder": "v1", "timezone": "Asia/Kolkata" }
}
